LICENSE
MANIFEST.in
README.md
package.json
setup.py
dash_geoman/Geoman.py
dash_geoman/__init__.py
dash_geoman/_imports_.py
dash_geoman/async-Geoman.js
dash_geoman/async-Geoman.js.map
dash_geoman/dash_geoman.min.js
dash_geoman/dash_geoman.min.js.map
dash_geoman/metadata.json
dash_geoman/package-info.json
dash_geoman.egg-info/PKG-INFO
dash_geoman.egg-info/SOURCES.txt
dash_geoman.egg-info/dependency_links.txt
dash_geoman.egg-info/requires.txt
dash_geoman.egg-info/top_level.txt