Metadata-Version: 2.1
Name: dash-geoman
Version: 0.1.0
Summary: leaflet-geoman component for Dash
Home-page: https://github.com/pikhovkin/dash-geoman
Author: Sergei Pikhovkin <s@pikhovkin.ru>
License: MIT
Keywords: dash,plotly,plotly-dash,geoman,leaflet,leaflet-geoman,map
Platform: UNKNOWN
Classifier: Environment :: Web Environment
Classifier: License :: OSI Approved :: MIT License
Classifier: Programming Language :: Python :: 2.7
Classifier: Programming Language :: Python :: 3
Classifier: Framework :: Dash
License-File: LICENSE
